csvengine/__init__.py
csvengine/main.py
csvengine-1.0.0.dist-info/LICENSE
csvengine-1.0.0.dist-info/METADATA
csvengine-1.0.0.dist-info/WHEEL
csvengine-1.0.0.dist-info/top_level.txt
csvengine-1.0.0.dist-info/RECORD
